LICENSE
README.md
setup.cfg
setup.py
src/Puffin/Dataset.py
src/Puffin/DatasetConfig.py
src/Puffin/DatasetLibrary.py
src/Puffin/__init__.py
src/Puffin/enums.py
src/Puffin/logger.py
src/Puffin.egg-info/PKG-INFO
src/Puffin.egg-info/SOURCES.txt
src/Puffin.egg-info/dependency_links.txt
src/Puffin.egg-info/requires.txt
src/Puffin.egg-info/top_level.txt